stl2mask/__init__.py
stl2mask/helpers.py
stl2mask/mask2stl.py
stl2mask/stl2mask.py
stl2mask-0.1.0.dist-info/METADATA
stl2mask-0.1.0.dist-info/WHEEL
stl2mask-0.1.0.dist-info/entry_points.txt
stl2mask-0.1.0.dist-info/licenses/LICENSE
stl2mask-0.1.0.dist-info/RECORD
