Metadata-Version: 2.4
Name: stl2mask
Version: 0.1.0
Summary: Convert STL segmentations to binary masks.
Author: Corné Haasjes, Jan-Willem Beenakker
Maintainer-email: MReye research group <zospy@mreye.nl>
License-File: LICENSE
Requires-Python: <3.14,>=3.10
Requires-Dist: click>=8.2.1
Requires-Dist: meshlib>=3.0.7.226
Requires-Dist: numpy>=2.0.0
Requires-Dist: simpleitk>=2.5.2
